wvpy/__init__.py
wvpy/assignment.py
wvpy/jtools.py
wvpy/ptools.py
wvpy/pysheet.py
wvpy/render_workbook.py
wvpy/util.py
wvpy-1.1.2.dist-info/LICENSE
wvpy-1.1.2.dist-info/METADATA
wvpy-1.1.2.dist-info/WHEEL
wvpy-1.1.2.dist-info/top_level.txt
wvpy-1.1.2.dist-info/RECORD
